_Mykytea.cpython-38-darwin.so
Mykytea.py
kytea.dylibs/libkytea.0.dylib
kytea-0.1.9.dist-info/RECORD
kytea-0.1.9.dist-info/LICENSE
kytea-0.1.9.dist-info/WHEEL
kytea-0.1.9.dist-info/top_level.txt
kytea-0.1.9.dist-info/METADATA
